{
    "frames":
    {
        "submarine01":
        {
            "frame":
            {
                "x":0,
                "y":0,
                "w":32,
                "h":32
            },
            "rotated":false,
            "trimmed":false,
            "spriteSourceSize":
            {
                "x":0,
                "y":0,
                "w":32,
                "h":32
            },
            "sourceSize":
            {
                "w":32,
                "h":32
            }
        },
        
        "submarine02":
        {
            "frame":
            {
                "x":0,
                "y":33,
                "w":32,
                "h":32
            },
            "rotated":false,
            "trimmed":false,
            "spriteSourceSize":
            {
                "x":0,
                "y":0,
                "w":32,
                "h":32
            },
            "sourceSize":
            {
                "w":32,
                "h":32
            }
        },

        "submarine03":
        {
            "frame":
            {
                "x":33,
                "y":0,
                "w":32,
                "h":32
            },
            "rotated":false,
            "trimmed":false,
            "spriteSourceSize":
            {
                "x":0,
                "y":0,
                "w":32,
                "h":32
            },
            "sourceSize":
            {
                "w":32,
                "h":32
            }
        },
        
        "submarine04":
        {
            "frame":
            {
                "x":33,
                "y":33,
                "w":32,
                "h":32
            },
            "rotated":false,
            "trimmed":false,
            "spriteSourceSize":
            {
                "x":0,
                "y":0,
                "w":32,
                "h":32
            },
            "sourceSize":
            {
                "w":32,
                "h":32
            }
        },
            
        "submarine05":
        {
            "frame":
            {
                "x":0,
                "y":66,
                "w":32,
                "h":32
            },
            "rotated":false,
            "trimmed":false,
            "spriteSourceSize":
            {
                "x":0,
                "y":0,
                "w":32,
                "h":32
            },
            "sourceSize":
            {
                "w":32,
                "h":32
            }
        },
        "submarine06":
        {
            "frame":
            {
                "x":33,
                "y":66,
                "w":32,
                "h":32
            },
            "rotated":false,
            "trimmed":false,
            "spriteSourceSize":
            {
                "x":0,
                "y":0,
                "w":32,
                "h":32
            },
            "sourceSize":
            {
                "w":32,
                "h":32
            }
        }
    },
    
    "meta":
    {
        "app":"https://www.leshylabs.com/apps/sstool/",
        "version":"Leshy SpriteSheet Tool v0.8.4",
        "image":"submarine.png",
        "size":
        {
            "w":65,
            "h":98
        },
        "scale":1
    }
}